Workbook
Name tblExpense: Table1[]

Sheet Dashboard
B1: Expense and Budget Dashboard
B3: Select month | C3: 45292
B5: Total spend | C5: =SUMIFS(Input!$F$5:$F$1004,Input!$I$5:$I$1004,$C$3) -> 62180.08
B6: Total budget | C6: ='Monthly Summary'!$B$17 -> 73300
B7: Remaining budget | C7: =C6-C5 -> 11119.92
B8: Categories over budget | C8: {=SUMPRODUCT(--(SUMIFS(Input!$F$5:$F$1004,Input!$D$5:$D$1004,Categories!$A$5:$A$16,Input!$I$5:$I$1004,$C$3)>Categories!$B$5:$B$16))} -> 4
B9: % of budget used | C9: =IF(C6=0,0,C5/C6) -> 0.84829577

Sheet Input
A1: Expense Transactions - January to October 2024
A4: Transaction ID | B4: Date | C4: Department | D4: Category | E4: Vendor / Description | F4: Amount (USD) | G4: Payment Method | H4: Status | I4: Month (helper)
A5: EXP-02401 | B5: 45292 | C5: Product | D5: Rent | E5: Landlord - Office Lease | F5: 15000 | G5: Bank Transfer | H5: Approved | I5: =DATE(YEAR(B5),MONTH(B5),1) -> 45292
A6: EXP-02402 | B6: 45293 | C6: Admin | D6: Travel | E6: Air India | F6: 1177.41 | G6: Corporate Card | H6: Pending | I6: =DATE(YEAR(B6),MONTH(B6),1) -> 45292
A7: EXP-02403 | B7: 45293 | C7: Marketing | D7: Travel | E7: Ola | F7: 467.27 | G7: Reimbursement | H7: Approved | I7: =DATE(YEAR(B7),MONTH(B7),1) -> 45292
A8: EXP-02404 | B8: 45293 | C8: Marketing | D8: Marketing | E8: Print Vendor | F8: 132.06 | G8: Purchase Order | H8: Approved | I8: =DATE(YEAR(B8),MONTH(B8),1) -> 45292
A9: EXP-02405 | B9: 45293 | C9: HR | D9: Meals & Entertainment | E9: Team Dinner | F9: 109.87 | G9: Corporate Card | H9: Pending | I9: =DATE(YEAR(B9),MONTH(B9),1) -> 45292
A10: EXP-02406 | B10: 45294 | C10: Operations | D10: Meals & Entertainment | E10: Cafe Coffee Day | F10: 347.68 | G10: Reimbursement | H10: Approved | I10: =DATE(YEAR(B10),MONTH(B10),1) -> 45292
A11: EXP-02407 | B11: 45294 | C11: Admin | D11: Office Supplies | E11: Staples | F11: 174.02 | G11: Corporate Card | H11: Pending | I11: =DATE(YEAR(B11),MONTH(B11),1) -> 45292
A12: EXP-02408 | B12: 45294 | C12: IT | D12: Software & Subscriptions | E12: Zoom | F12: 621.57 | G12: Purchase Order | H12: Approved | I12: =DATE(YEAR(B12),MONTH(B12),1) -> 45292
A13: EXP-02409 | B13: 45295 | C13: Marketing | D13: Telephone & Internet | E13: Airtel Business | F13: 72.34 | G13: Bank Transfer | H13: Approved | I13: =DATE(YEAR(B13),MONTH(B13),1) -> 45292
A14: EXP-02410 | B14: 45295 | C14: Marketing | D14: Utilities | E14: Water Authority | F14: 213.5 | G14: Bank Transfer | H14: Approved | I14: =DATE(YEAR(B14),MONTH(B14),1) -> 45292
A15: EXP-02411 | B15: 45296 | C15: Sales | D15: Miscellaneous | E15: Bank Charges | F15: 18.59 | G15: Cash | H15: Approved | I15: =DATE(YEAR(B15),MONTH(B15),1) -> 45292
A16: EXP-02412 | B16: 45296 | C16: Finance | D16: Equipment & IT | E16: Cisco Networking | F16: 1163.44 | G16: Purchase Order | H16: Approved | I16: =DATE(YEAR(B16),MONTH(B16),1) -> 45292
... A1004: EXP-03400 | B1004: 45596 | C1004: Admin | D1004: Meals & Entertainment | E1004: Subway | F1004: 207.99 | G1004: Reimbursement | H1004: Pending | I1004: =DATE(YEAR(B1004),MONTH(B1004),1) -> 45566

Sheet Categories
A1: Category List and Monthly Budget
A2: Monthly budget (USD) is the planning limit per category. Use this list for data validation dropdowns.
A4: Category | B4: Monthly Budget (USD) | C4: Typical Vendor Examples
A5: Travel | B5: 13400 | C5: Air India, IndiGo, Uber
A6: Meals & Entertainment | B6: 2200 | C6: Starbucks, Client Lunch - Bistro, Team Dinner
A7: Office Supplies | B7: 900 | C7: Staples, Amazon Business, Office Depot
A8: Software & Subscriptions | B8: 4400 | C8: Microsoft 365, Adobe Creative Cloud, Slack
A9: Utilities | B9: 2200 | C9: City Power Board, Water Authority, Gas Supply Co.
A10: Rent | B10: 15000 | C10: Landlord - Office Lease
A11: Marketing | B11: 14300 | C11: Google Ads, Meta Ads, LinkedIn Ads
A12: Training & Development | B12: 4200 | C12: Coursera for Business, Udemy Business, Local Workshop Provider
A13: Equipment & IT | B13: 5500 | C13: Dell, Lenovo, Logitech
A14: Telephone & Internet | B14: 1400 | C14: Airtel Business, Jio Business, ACT Fibernet
A15: Professional Services | B15: 8500 | C15: Legal Associates LLP, Audit & Tax Partners, HR Consultants Inc.
A16: Miscellaneous | B16: 1300 | C16: Pantry Supplies, Courier Service, Bank Charges

Sheet Monthly Summary
A4: Category | B4: Monthly Budget | C4: 45292 | D4: 45323 | E4: 45352 | F4: 45383 | G4: 45413 | H4: 45444 | I4: 45474 | J4: 45505 | K4: 45536 | L4: 45566 | M4: YTD Actual | N4: YTD Budget | O4: Variance | P4: % Used | Q4: Alert
A5: =Categories!A5 -> Travel | B5: =Categories!B5 -> 13400 | C5: =SUMIFS(Input!$F$5:$F$1004,Input!$D$5:$D$1004,$A5,Input!$I$5:$I$1004,C$4) -> 10265.88 | D5: =SUMIFS(Input!$F$5:$F$1004,Input!$D$5:$D$1004,$A5,Input!$I$5:$I$1004,D$4) -> 11208.75 | E5: =SUMIFS(Input!$F$5:$F$1004,Input!$D$5:$D$1004,$A5,Input!$I$5:$I$1004,E$4) -> 12692.15 | F5: =SUMIFS(Input!$F$5:$F$1004,Input!$D$5:$D$1004,$A5,Input!$I$5:$I$1004,F$4) -> 12410 | G5: =SUMIFS(Input!$F$5:$F$1004,Input!$D$5:$D$1004,$A5,Input!$I$5:$I$1004,G$4) -> 11053.91 | H5: =SUMIFS(Input!$F$5:$F$1004,Input!$D$5:$D$1004,$A5,Input!$I$5:$I$1004,H$4) -> 6305.87 | I5: =SUMIFS(Input!$F$5:$F$1004,Input!$D$5:$D$1004,$A5,Input!$I$5:$I$1004,I$4) -> 11445.74 | J5: =SUMIFS(Input!$F$5:$F$1004,Input!$D$5:$D$1004,$A5,Input!$I$5:$I$1004,J$4) -> 16088.83 | ... L5: =SUMIFS(Input!$F$5:$F$1004,Input!$D$5:$D$1004,$A5,Input!$I$5:$I$1004,L$4) -> 18678.57 | M5: =SUM(C5:L5) -> 123004.92 | N5: =B5*COUNT($C$4:$L$4) -> 134000 | O5: =N5-M5 -> 10995.08 | P5: =IF(N5=0,0,M5/N5) -> 0.91794716 | Q5: =IF(P5>1,"OVER BUDGET",IF(P5>=0.8,"WARNING","OK")) -> WARNING
A6: =Categories!A6 -> Meals & Entertainment | B6: =Categories!B6 -> 2200 | C6: =SUMIFS(Input!$F$5:$F$1004,Input!$D$5:$D$1004,$A6,Input!$I$5:$I$1004,C$4) -> 2559.04 | D6: =SUMIFS(Input!$F$5:$F$1004,Input!$D$5:$D$1004,$A6,Input!$I$5:$I$1004,D$4) -> 2861.65 | E6: =SUMIFS(Input!$F$5:$F$1004,Input!$D$5:$D$1004,$A6,Input!$I$5:$I$1004,E$4) -> 2920.73 | F6: =SUMIFS(Input!$F$5:$F$1004,Input!$D$5:$D$1004,$A6,Input!$I$5:$I$1004,F$4) -> 1605.84 | G6: =SUMIFS(Input!$F$5:$F$1004,Input!$D$5:$D$1004,$A6,Input!$I$5:$I$1004,G$4) -> 3090.9 | H6: =SUMIFS(Input!$F$5:$F$1004,Input!$D$5:$D$1004,$A6,Input!$I$5:$I$1004,H$4) -> 1931.68 | I6: =SUMIFS(Input!$F$5:$F$1004,Input!$D$5:$D$1004,$A6,Input!$I$5:$I$1004,I$4) -> 751.79 | J6: =SUMIFS(Input!$F$5:$F$1004,Input!$D$5:$D$1004,$A6,Input!$I$5:$I$1004,J$4) -> 2310.93 | ... L6: =SUMIFS(Input!$F$5:$F$1004,Input!$D$5:$D$1004,$A6,Input!$I$5:$I$1004,L$4) -> 1956.73 | M6: =SUM(C6:L6) -> 22171.19 | N6: =B6*COUNT($C$4:$L$4) -> 22000 | O6: =N6-M6 -> -171.19 | P6: =IF(N6=0,0,M6/N6) -> 1.0077814 | Q6: =IF(P6>1,"OVER BUDGET",IF(P6>=0.8,"WARNING","OK")) -> OVER BUDGET
A7: =Categories!A7 -> Office Supplies | B7: =Categories!B7 -> 900 | C7: =SUMIFS(Input!$F$5:$F$1004,Input!$D$5:$D$1004,$A7,Input!$I$5:$I$1004,C$4) -> 984 | D7: =SUMIFS(Input!$F$5:$F$1004,Input!$D$5:$D$1004,$A7,Input!$I$5:$I$1004,D$4) -> 1258.71 | E7: =SUMIFS(Input!$F$5:$F$1004,Input!$D$5:$D$1004,$A7,Input!$I$5:$I$1004,E$4) -> 961.51 | F7: =SUMIFS(Input!$F$5:$F$1004,Input!$D$5:$D$1004,$A7,Input!$I$5:$I$1004,F$4) -> 1034.66 | G7: =SUMIFS(Input!$F$5:$F$1004,Input!$D$5:$D$1004,$A7,Input!$I$5:$I$1004,G$4) -> 1054.5 | H7: =SUMIFS(Input!$F$5:$F$1004,Input!$D$5:$D$1004,$A7,Input!$I$5:$I$1004,H$4) -> 778.33 | I7: =SUMIFS(Input!$F$5:$F$1004,Input!$D$5:$D$1004,$A7,Input!$I$5:$I$1004,I$4) -> 727.33 | J7: =SUMIFS(Input!$F$5:$F$1004,Input!$D$5:$D$1004,$A7,Input!$I$5:$I$1004,J$4) -> 1050.59 | ... L7: =SUMIFS(Input!$F$5:$F$1004,Input!$D$5:$D$1004,$A7,Input!$I$5:$I$1004,L$4) -> 712.84 | M7: =SUM(C7:L7) -> 9275.15 | N7: =B7*COUNT($C$4:$L$4) -> 9000 | O7: =N7-M7 -> -275.15 | P7: =IF(N7=0,0,M7/N7) -> 1.0305722 | Q7: =IF(P7>1,"OVER BUDGET",IF(P7>=0.8,"WARNING","OK")) -> OVER BUDGET
A8: =Categories!A8 -> Software & Subscriptions | B8: =Categories!B8 -> 4400 | C8: =SUMIFS(Input!$F$5:$F$1004,Input!$D$5:$D$1004,$A8,Input!$I$5:$I$1004,C$4) -> 4570.25 | D8: =SUMIFS(Input!$F$5:$F$1004,Input!$D$5:$D$1004,$A8,Input!$I$5:$I$1004,D$4) -> 3676.36 | E8: =SUMIFS(Input!$F$5:$F$1004,Input!$D$5:$D$1004,$A8,Input!$I$5:$I$1004,E$4) -> 4371.72 | F8: =SUMIFS(Input!$F$5:$F$1004,Input!$D$5:$D$1004,$A8,Input!$I$5:$I$1004,F$4) -> 5032.25 | G8: =SUMIFS(Input!$F$5:$F$1004,Input!$D$5:$D$1004,$A8,Input!$I$5:$I$1004,G$4) -> 6459.38 | H8: =SUMIFS(Input!$F$5:$F$1004,Input!$D$5:$D$1004,$A8,Input!$I$5:$I$1004,H$4) -> 3595.5 | I8: =SUMIFS(Input!$F$5:$F$1004,Input!$D$5:$D$1004,$A8,Input!$I$5:$I$1004,I$4) -> 4249.72 | J8: =SUMIFS(Input!$F$5:$F$1004,Input!$D$5:$D$1004,$A8,Input!$I$5:$I$1004,J$4) -> 2177.81 | ... L8: =SUMIFS(Input!$F$5:$F$1004,Input!$D$5:$D$1004,$A8,Input!$I$5:$I$1004,L$4) -> 6215 | M8: =SUM(C8:L8) -> 42116.71 | N8: =B8*COUNT($C$4:$L$4) -> 44000 | O8: =N8-M8 -> 1883.29 | P8: =IF(N8=0,0,M8/N8) -> 0.95719795 | Q8: =IF(P8>1,"OVER BUDGET",IF(P8>=0.8,"WARNING","OK")) -> WARNING
A9: =Categories!A9 -> Utilities | B9: =Categories!B9 -> 2200 | C9: =SUMIFS(Input!$F$5:$F$1004,Input!$D$5:$D$1004,$A9,Input!$I$5:$I$1004,C$4) -> 1414.37 | D9: =SUMIFS(Input!$F$5:$F$1004,Input!$D$5:$D$1004,$A9,Input!$I$5:$I$1004,D$4) -> 4724.5 | E9: =SUMIFS(Input!$F$5:$F$1004,Input!$D$5:$D$1004,$A9,Input!$I$5:$I$1004,E$4) -> 2162.62 | F9: =SUMIFS(Input!$F$5:$F$1004,Input!$D$5:$D$1004,$A9,Input!$I$5:$I$1004,F$4) -> 3865.8 | G9: =SUMIFS(Input!$F$5:$F$1004,Input!$D$5:$D$1004,$A9,Input!$I$5:$I$1004,G$4) -> 2018.07 | H9: =SUMIFS(Input!$F$5:$F$1004,Input!$D$5:$D$1004,$A9,Input!$I$5:$I$1004,H$4) -> 1261.93 | I9: =SUMIFS(Input!$F$5:$F$1004,Input!$D$5:$D$1004,$A9,Input!$I$5:$I$1004,I$4) -> 2185.94 | J9: =SUMIFS(Input!$F$5:$F$1004,Input!$D$5:$D$1004,$A9,Input!$I$5:$I$1004,J$4) -> 1909.84 | ... L9: =SUMIFS(Input!$F$5:$F$1004,Input!$D$5:$D$1004,$A9,Input!$I$5:$I$1004,L$4) -> 1069.06 | M9: =SUM(C9:L9) -> 22952.6 | N9: =B9*COUNT($C$4:$L$4) -> 22000 | O9: =N9-M9 -> -952.6 | P9: =IF(N9=0,0,M9/N9) -> 1.0433 | Q9: =IF(P9>1,"OVER BUDGET",IF(P9>=0.8,"WARNING","OK")) -> OVER BUDGET
A10: =Categories!A10 -> Rent | B10: =Categories!B10 -> 15000 | C10: =SUMIFS(Input!$F$5:$F$1004,Input!$D$5:$D$1004,$A10,Input!$I$5:$I$1004,C$4) -> 15000 | D10: =SUMIFS(Input!$F$5:$F$1004,Input!$D$5:$D$1004,$A10,Input!$I$5:$I$1004,D$4) -> 15000 | E10: =SUMIFS(Input!$F$5:$F$1004,Input!$D$5:$D$1004,$A10,Input!$I$5:$I$1004,E$4) -> 15000 | F10: =SUMIFS(Input!$F$5:$F$1004,Input!$D$5:$D$1004,$A10,Input!$I$5:$I$1004,F$4) -> 15000 | G10: =SUMIFS(Input!$F$5:$F$1004,Input!$D$5:$D$1004,$A10,Input!$I$5:$I$1004,G$4) -> 15000 | H10: =SUMIFS(Input!$F$5:$F$1004,Input!$D$5:$D$1004,$A10,Input!$I$5:$I$1004,H$4) -> 15000 | I10: =SUMIFS(Input!$F$5:$F$1004,Input!$D$5:$D$1004,$A10,Input!$I$5:$I$1004,I$4) -> 15000 | J10: =SUMIFS(Input!$F$5:$F$1004,Input!$D$5:$D$1004,$A10,Input!$I$5:$I$1004,J$4) -> 15000 | ... L10: =SUMIFS(Input!$F$5:$F$1004,Input!$D$5:$D$1004,$A10,Input!$I$5:$I$1004,L$4) -> 15000 | M10: =SUM(C10:L10) -> 150000 | N10: =B10*COUNT($C$4:$L$4) -> 150000 | O10: =N10-M10 -> 0 | P10: =IF(N10=0,0,M10/N10) -> 1 | Q10: =IF(P10>1,"OVER BUDGET",IF(P10>=0.8,"WARNING","OK")) -> WARNING
A11: =Categories!A11 -> Marketing | B11: =Categories!B11 -> 14300 | C11: =SUMIFS(Input!$F$5:$F$1004,Input!$D$5:$D$1004,$A11,Input!$I$5:$I$1004,C$4) -> 11427.12 | D11: =SUMIFS(Input!$F$5:$F$1004,Input!$D$5:$D$1004,$A11,Input!$I$5:$I$1004,D$4) -> 14949.8 | E11: =SUMIFS(Input!$F$5:$F$1004,Input!$D$5:$D$1004,$A11,Input!$I$5:$I$1004,E$4) -> 15411.52 | F11: =SUMIFS(Input!$F$5:$F$1004,Input!$D$5:$D$1004,$A11,Input!$I$5:$I$1004,F$4) -> 19515.73 | G11: =SUMIFS(Input!$F$5:$F$1004,Input!$D$5:$D$1004,$A11,Input!$I$5:$I$1004,G$4) -> 12372.2 | H11: =SUMIFS(Input!$F$5:$F$1004,Input!$D$5:$D$1004,$A11,Input!$I$5:$I$1004,H$4) -> 10208.52 | I11: =SUMIFS(Input!$F$5:$F$1004,Input!$D$5:$D$1004,$A11,Input!$I$5:$I$1004,I$4) -> 7894.18 | J11: =SUMIFS(Input!$F$5:$F$1004,Input!$D$5:$D$1004,$A11,Input!$I$5:$I$1004,J$4) -> 11697.09 | ... L11: =SUMIFS(Input!$F$5:$F$1004,Input!$D$5:$D$1004,$A11,Input!$I$5:$I$1004,L$4) -> 14354.88 | M11: =SUM(C11:L11) -> 127936.62 | N11: =B11*COUNT($C$4:$L$4) -> 143000 | O11: =N11-M11 -> 15063.38 | P11: =IF(N11=0,0,M11/N11) -> 0.89466168 | Q11: =IF(P11>1,"OVER BUDGET",IF(P11>=0.8,"WARNING","OK")) -> WARNING
A12: =Categories!A12 -> Training & Development | B12: =Categories!B12 -> 4200 | C12: =SUMIFS(Input!$F$5:$F$1004,Input!$D$5:$D$1004,$A12,Input!$I$5:$I$1004,C$4) -> 3707.64 | D12: =SUMIFS(Input!$F$5:$F$1004,Input!$D$5:$D$1004,$A12,Input!$I$5:$I$1004,D$4) -> 4429.91 | E12: =SUMIFS(Input!$F$5:$F$1004,Input!$D$5:$D$1004,$A12,Input!$I$5:$I$1004,E$4) -> 8645.17 | F12: =SUMIFS(Input!$F$5:$F$1004,Input!$D$5:$D$1004,$A12,Input!$I$5:$I$1004,F$4) -> 3509.05 | G12: =SUMIFS(Input!$F$5:$F$1004,Input!$D$5:$D$1004,$A12,Input!$I$5:$I$1004,G$4) -> 4892.18 | H12: =SUMIFS(Input!$F$5:$F$1004,Input!$D$5:$D$1004,$A12,Input!$I$5:$I$1004,H$4) -> 3220.99 | I12: =SUMIFS(Input!$F$5:$F$1004,Input!$D$5:$D$1004,$A12,Input!$I$5:$I$1004,I$4) -> 2973.69 | J12: =SUMIFS(Input!$F$5:$F$1004,Input!$D$5:$D$1004,$A12,Input!$I$5:$I$1004,J$4) -> 8409.4 | ... L12: =SUMIFS(Input!$F$5:$F$1004,Input!$D$5:$D$1004,$A12,Input!$I$5:$I$1004,L$4) -> 2981.86 | M12: =SUM(C12:L12) -> 45945.1 | N12: =B12*COUNT($C$4:$L$4) -> 42000 | O12: =N12-M12 -> -3945.1 | P12: =IF(N12=0,0,M12/N12) -> 1.093931 | Q12: =IF(P12>1,"OVER BUDGET",IF(P12>=0.8,"WARNING","OK")) -> OVER BUDGET
A13: =Categories!A13 -> Equipment & IT | B13: =Categories!B13 -> 5500 | C13: =SUMIFS(Input!$F$5:$F$1004,Input!$D$5:$D$1004,$A13,Input!$I$5:$I$1004,C$4) -> 6380.36 | D13: =SUMIFS(Input!$F$5:$F$1004,Input!$D$5:$D$1004,$A13,Input!$I$5:$I$1004,D$4) -> 3162.25 | E13: =SUMIFS(Input!$F$5:$F$1004,Input!$D$5:$D$1004,$A13,Input!$I$5:$I$1004,E$4) -> 4245.71 | F13: =SUMIFS(Input!$F$5:$F$1004,Input!$D$5:$D$1004,$A13,Input!$I$5:$I$1004,F$4) -> 4992.04 | G13: =SUMIFS(Input!$F$5:$F$1004,Input!$D$5:$D$1004,$A13,Input!$I$5:$I$1004,G$4) -> 11406.73 | H13: =SUMIFS(Input!$F$5:$F$1004,Input!$D$5:$D$1004,$A13,Input!$I$5:$I$1004,H$4) -> 5540.65 | I13: =SUMIFS(Input!$F$5:$F$1004,Input!$D$5:$D$1004,$A13,Input!$I$5:$I$1004,I$4) -> 2520.13 | J13: =SUMIFS(Input!$F$5:$F$1004,Input!$D$5:$D$1004,$A13,Input!$I$5:$I$1004,J$4) -> 9715.06 | ... L13: =SUMIFS(Input!$F$5:$F$1004,Input!$D$5:$D$1004,$A13,Input!$I$5:$I$1004,L$4) -> 687.49 | M13: =SUM(C13:L13) -> 56048.16 | N13: =B13*COUNT($C$4:$L$4) -> 55000 | O13: =N13-M13 -> -1048.16 | P13: =IF(N13=0,0,M13/N13) -> 1.0190575 | Q13: =IF(P13>1,"OVER BUDGET",IF(P13>=0.8,"WARNING","OK")) -> OVER BUDGET
A14: =Categories!A14 -> Telephone & Internet | B14: =Categories!B14 -> 1400 | C14: =SUMIFS(Input!$F$5:$F$1004,Input!$D$5:$D$1004,$A14,Input!$I$5:$I$1004,C$4) -> 1211.1 | D14: =SUMIFS(Input!$F$5:$F$1004,Input!$D$5:$D$1004,$A14,Input!$I$5:$I$1004,D$4) -> 1344.49 | E14: =SUMIFS(Input!$F$5:$F$1004,Input!$D$5:$D$1004,$A14,Input!$I$5:$I$1004,E$4) -> 2067.52 | F14: =SUMIFS(Input!$F$5:$F$1004,Input!$D$5:$D$1004,$A14,Input!$I$5:$I$1004,F$4) -> 755.42 | G14: =SUMIFS(Input!$F$5:$F$1004,Input!$D$5:$D$1004,$A14,Input!$I$5:$I$1004,G$4) -> 1559.73 | H14: =SUMIFS(Input!$F$5:$F$1004,Input!$D$5:$D$1004,$A14,Input!$I$5:$I$1004,H$4) -> 1217.65 | I14: =SUMIFS(Input!$F$5:$F$1004,Input!$D$5:$D$1004,$A14,Input!$I$5:$I$1004,I$4) -> 1129.44 | J14: =SUMIFS(Input!$F$5:$F$1004,Input!$D$5:$D$1004,$A14,Input!$I$5:$I$1004,J$4) -> 650.3 | ... L14: =SUMIFS(Input!$F$5:$F$1004,Input!$D$5:$D$1004,$A14,Input!$I$5:$I$1004,L$4) -> 1439.51 | M14: =SUM(C14:L14) -> 11901.79 | N14: =B14*COUNT($C$4:$L$4) -> 14000 | O14: =N14-M14 -> 2098.21 | P14: =IF(N14=0,0,M14/N14) -> 0.85012786 | Q14: =IF(P14>1,"OVER BUDGET",IF(P14>=0.8,"WARNING","OK")) -> WARNING
A15: =Categories!A15 -> Professional Services | B15: =Categories!B15 -> 8500 | C15: =SUMIFS(Input!$F$5:$F$1004,Input!$D$5:$D$1004,$A15,Input!$I$5:$I$1004,C$4) -> 3576.36 | D15: =SUMIFS(Input!$F$5:$F$1004,Input!$D$5:$D$1004,$A15,Input!$I$5:$I$1004,D$4) -> 4703.95 | E15: =SUMIFS(Input!$F$5:$F$1004,Input!$D$5:$D$1004,$A15,Input!$I$5:$I$1004,E$4) -> 4063.73 | F15: =SUMIFS(Input!$F$5:$F$1004,Input!$D$5:$D$1004,$A15,Input!$I$5:$I$1004,F$4) -> 10787.26 | G15: =SUMIFS(Input!$F$5:$F$1004,Input!$D$5:$D$1004,$A15,Input!$I$5:$I$1004,G$4) -> 9592.95 | H15: =SUMIFS(Input!$F$5:$F$1004,Input!$D$5:$D$1004,$A15,Input!$I$5:$I$1004,H$4) -> 8196.88 | I15: =SUMIFS(Input!$F$5:$F$1004,Input!$D$5:$D$1004,$A15,Input!$I$5:$I$1004,I$4) -> 13046.75 | J15: =SUMIFS(Input!$F$5:$F$1004,Input!$D$5:$D$1004,$A15,Input!$I$5:$I$1004,J$4) -> 2902.85 | ... L15: =SUMIFS(Input!$F$5:$F$1004,Input!$D$5:$D$1004,$A15,Input!$I$5:$I$1004,L$4) -> 3624.65 | M15: =SUM(C15:L15) -> 74506.67 | N15: =B15*COUNT($C$4:$L$4) -> 85000 | O15: =N15-M15 -> 10493.33 | P15: =IF(N15=0,0,M15/N15) -> 0.87654906 | Q15: =IF(P15>1,"OVER BUDGET",IF(P15>=0.8,"WARNING","OK")) -> WARNING
A16: =Categories!A16 -> Miscellaneous | B16: =Categories!B16 -> 1300 | C16: =SUMIFS(Input!$F$5:$F$1004,Input!$D$5:$D$1004,$A16,Input!$I$5:$I$1004,C$4) -> 1083.96 | D16: =SUMIFS(Input!$F$5:$F$1004,Input!$D$5:$D$1004,$A16,Input!$I$5:$I$1004,D$4) -> 1032.63 | E16: =SUMIFS(Input!$F$5:$F$1004,Input!$D$5:$D$1004,$A16,Input!$I$5:$I$1004,E$4) -> 1953.49 | F16: =SUMIFS(Input!$F$5:$F$1004,Input!$D$5:$D$1004,$A16,Input!$I$5:$I$1004,F$4) -> 1742.72 | G16: =SUMIFS(Input!$F$5:$F$1004,Input!$D$5:$D$1004,$A16,Input!$I$5:$I$1004,G$4) -> 1208.42 | H16: =SUMIFS(Input!$F$5:$F$1004,Input!$D$5:$D$1004,$A16,Input!$I$5:$I$1004,H$4) -> 699.97 | I16: =SUMIFS(Input!$F$5:$F$1004,Input!$D$5:$D$1004,$A16,Input!$I$5:$I$1004,I$4) -> 815.62 | J16: =SUMIFS(Input!$F$5:$F$1004,Input!$D$5:$D$1004,$A16,Input!$I$5:$I$1004,J$4) -> 1068.42 | ... L16: =SUMIFS(Input!$F$5:$F$1004,Input!$D$5:$D$1004,$A16,Input!$I$5:$I$1004,L$4) -> 1264.68 | M16: =SUM(C16:L16) -> 11882.13 | N16: =B16*COUNT($C$4:$L$4) -> 13000 | O16: =N16-M16 -> 1117.87 | P16: =IF(N16=0,0,M16/N16) -> 0.91401 | Q16: =IF(P16>1,"OVER BUDGET",IF(P16>=0.8,"WARNING","OK")) -> WARNING
A17: Total | B17: =SUM(B5:B16) -> 73300 | C17: =SUM(C5:C16) -> 62180.08 | D17: =SUM(D5:D16) -> 68353 | E17: =SUM(E5:E16) -> 74495.87 | F17: =SUM(F5:F16) -> 80250.77 | G17: =SUM(G5:G16) -> 79708.97 | H17: =SUM(H5:H16) -> 57957.97 | I17: =SUM(I5:I16) -> 62740.33 | ... O17: =SUM(O5:O16) -> 35258.96 | P17: =IF(N17=0,0,M17/N17) -> 0.95189774 | Q17: =IF(P17>1,"OVER BUDGET",IF(P17>=0.8,"WARNING","OK")) -> WARNING
A20: Month | B20: Budget | C20: Actual
A21: =C4 -> 45292 | B21: =$B$17 -> 73300 | C21: =SUMIFS(Input!$F$5:$F$1004,Input!$I$5:$I$1004,A21) -> 62180.08
A22: =EDATE(A21,1) -> 45323 | B22: =$B$17 -> 73300 | C22: =SUMIFS(Input!$F$5:$F$1004,Input!$I$5:$I$1004,A22) -> 68353
A23: =EDATE(A22,1) -> 45352 | B23: =$B$17 -> 73300 | C23: =SUMIFS(Input!$F$5:$F$1004,Input!$I$5:$I$1004,A23) -> 74495.87
A24: =EDATE(A23,1) -> 45383 | B24: =$B$17 -> 73300 | C24: =SUMIFS(Input!$F$5:$F$1004,Input!$I$5:$I$1004,A24) -> 80250.77
A25: =EDATE(A24,1) -> 45413 | B25: =$B$17 -> 73300 | C25: =SUMIFS(Input!$F$5:$F$1004,Input!$I$5:$I$1004,A25) -> 79708.97
A26: =EDATE(A25,1) -> 45444 | B26: =$B$17 -> 73300 | C26: =SUMIFS(Input!$F$5:$F$1004,Input!$I$5:$I$1004,A26) -> 57957.97
A27: =EDATE(A26,1) -> 45474 | B27: =$B$17 -> 73300 | C27: =SUMIFS(Input!$F$5:$F$1004,Input!$I$5:$I$1004,A27) -> 62740.33
A28: =EDATE(A27,1) -> 45505 | B28: =$B$17 -> 73300 | C28: =SUMIFS(Input!$F$5:$F$1004,Input!$I$5:$I$1004,A28) -> 72981.12
A29: =EDATE(A28,1) -> 45536 | B29: =$B$17 -> 73300 | C29: =SUMIFS(Input!$F$5:$F$1004,Input!$I$5:$I$1004,A29) -> 71087.66
A30: =EDATE(A29,1) -> 45566 | B30: =$B$17 -> 73300 | C30: =SUMIFS(Input!$F$5:$F$1004,Input!$I$5:$I$1004,A30) -> 67985.27

Sheet Lists
A1: Department | B1: Payment Method | C1: Status | D1: Month
A2: Sales | B2: Corporate Card | C2: Approved | D2: 45292
A3: Marketing | B3: Reimbursement | C3: Pending | D3: 45323
A4: Finance | B4: Bank Transfer | C4: Rejected | D4: 45352
A5: HR | B5: Auto Debit | D5: 45383
A6: IT | B6: Purchase Order | D6: 45413
A7: Operations | B7: Cash | D7: 45444
A8: Admin | D8: 45474
A9: Product | D9: 45505
D10: 45536
D11: 45566
